cert2temp/__init__.py
cert2temp/__version__.py
cert2temp/ssl_utils.py
cert2temp-0.1.0.dist-info/licenses/LICENSE
cert2temp-0.1.0.dist-info/METADATA
cert2temp-0.1.0.dist-info/WHEEL
cert2temp-0.1.0.dist-info/top_level.txt
cert2temp-0.1.0.dist-info/RECORD
