Metadata-Version: 2.4
Name: cert2temp
Version: 0.1.0
Summary: SSL Certificate Temporary Folder Management Utility
Home-page: https://github.com/minicom365/cert2temp
Author: Minicom
Author-email: Minicom <3387910@naver.com>
Maintainer-email: Minicom <3387910@naver.com>
License: MIT License
Project-URL: Homepage, https://github.com/minicom365/cert2temp
Project-URL: Documentation, https://cert2temp.readthedocs.io/
Project-URL: Repository, https://github.com/minicom365/cert2temp
Project-URL: Issues, https://github.com/minicom365/cert2temp/issues
Project-URL: Changelog, https://github.com/minicom365/cert2temp/blob/main/CHANGELOG.md
Keywords: ssl,certificate,temp,temporary,folder,path,unicode,ascii,cross-platform
Classifier: Development Status :: 4 - Beta
Classifier: Intended Audience :: Developers
Classifier: License :: OSI Approved :: MIT License
Classifier: Operating System :: OS Independent
Classifier: Programming Language :: Python :: 3
Classifier: Programming Language :: Python :: 3.8
Classifier: Programming Language :: Python :: 3.9
Classifier: Programming Language :: Python :: 3.10
Classifier: Programming Language :: Python :: 3.11
Classifier: Programming Language :: Python :: 3.12
Classifier: Topic :: Security
Classifier: Topic :: System :: Networking
Classifier: Topic :: Utilities
Requires-Python: >=3.8
License-File: LICENSE
Requires-Dist: requests>=2.25.0
Requires-Dist: certifi>=2020.12.5
Provides-Extra: dev
Requires-Dist: pytest>=7.0; extra == "dev"
Requires-Dist: pytest-cov; extra == "dev"
Requires-Dist: black; extra == "dev"
Requires-Dist: flake8; extra == "dev"
Requires-Dist: mypy; extra == "dev"
Provides-Extra: test
Requires-Dist: pytest>=7.0; extra == "test"
Requires-Dist: pytest-cov; extra == "test"
Provides-Extra: curl
Requires-Dist: curl-cffi>=0.6.0; extra == "curl"
Dynamic: author
Dynamic: home-page
Dynamic: license-file
Dynamic: requires-python
